perky/__init__.py
perky/tokenize.py
perky/transform.py
perky/utility.py
perky-0.9.2.dist-info/LICENSE
perky-0.9.2.dist-info/WHEEL
perky-0.9.2.dist-info/METADATA
perky-0.9.2.dist-info/RECORD
