Metadata-Version: 2.1
Name: perky
Version: 0.9.2
Summary: A simple, Pythonic file format.  Same interface as the
Home-page: https://github.com/larryhastings/perky/
Author: Larry Hastings
Author-email: larry@hastings.org
Requires-Python: >=3.6
Classifier: Intended Audience :: Developers
Classifier: License :: OSI Approved :: MIT License
Classifier: Programming Language :: Python :: 3
Classifier: Programming Language :: Python :: 3.6
Classifier: Programming Language :: Python :: 3.7
Classifier: Programming Language :: Python :: 3.8
Classifier: Programming Language :: Python :: 3.9
Classifier: Programming Language :: Python :: 3.10
Classifier: Programming Language :: Python :: 3.11
Classifier: Programming Language :: Python :: 3.12
